bris/__init__.py
bris/__main__.py
bris/callbacks.py
bris/checkpoint.py
bris/ddp_strategy.py
bris/forcings.py
bris/inference.py
bris/inspect.py
bris/observations.py
bris/predict_metadata.py
bris/projections.py
bris/routes.py
bris/units.py
bris/utils.py
bris/writer.py
bris/conventions/__init__.py
bris/conventions/anemoi.py
bris/conventions/cf.py
bris/conventions/metno.py
bris/data/__init__.py
bris/data/datamodule.py
bris/data/dataset.py
bris/data/grid_indices.py
bris/data/legacy/__init__.py
bris/data/legacy/dataset.py
bris/data/legacy/utils.py
bris/data/legacy/distributed/__init__.py
bris/data/legacy/distributed/strategy.py
bris/model/__init__.py
bris/model/basepredictor.py
bris/model/brispredictor.py
bris/model/model_utils.py
bris/model/multiencdecpredictor.py
bris/outputs/__init__.py
bris/outputs/intermediate.py
bris/outputs/netcdf.py
bris/outputs/verif.py
bris/schema/schema.json
bris/sources/__init__.py
bris/sources/anemoidataset.py
bris/sources/azurestorage.py
bris/sources/frost.py
bris/sources/verif.py
bris-0.2.0.dist-info/licenses/LICENSE
bris-0.2.0.dist-info/METADATA
bris-0.2.0.dist-info/WHEEL
bris-0.2.0.dist-info/entry_points.txt
bris-0.2.0.dist-info/top_level.txt
bris-0.2.0.dist-info/RECORD
