Metadata-Version: 2.4
Name: bris
Version: 0.2.0
Summary: Package for running inference of Anemoi models
Author-email: Magnus Sikora Ingstad <magnusi@met.no>, Aram Salihi <arams@met.no>, Thomas Nipen <thomasn@met.no>, "Håvard H. Haugen" <havardhh@met.no>, Lars Falk-Petersen <larsfp@met.no>
License:                                  Apache License
Keywords: meteorology,forecast
Classifier: Development Status :: 3 - Alpha
Classifier: License :: OSI Approved :: Apache Software License
Classifier: Operating System :: OS Independent
Classifier: Programming Language :: Python :: 3 :: Only
Classifier: Programming Language :: Python :: 3.9
Classifier: Programming Language :: Python :: 3.10
Classifier: Programming Language :: Python :: 3.11
Classifier: Programming Language :: Python :: 3.12
Classifier: Programming Language :: Python :: Implementation :: CPython
Classifier: Programming Language :: Python :: Implementation :: PyPy
Requires-Python: >=3.9
License-File: LICENSE
Requires-Dist: anemoi-datasets>=0.5.16
Requires-Dist: gridpp~=0.7.0
Requires-Dist: hydra-core~=1.3.0
Requires-Dist: numpy~=1.26.0
Requires-Dist: pyproj~=3.7.0
Requires-Dist: pytorch-lightning>=2.1
Requires-Dist: scipy~=1.15.0
Requires-Dist: torch<2.6.0
Requires-Dist: torch_geometric~=2.4.0
Requires-Dist: torchinfo~=1.8.0
Requires-Dist: tqdm~=4.67.1
Requires-Dist: verif~=1.3.0
Requires-Dist: zarr<=2.17
Requires-Dist: numcodecs<0.16.0
Requires-Dist: pip~=25.1.0
Provides-Extra: tests
Requires-Dist: tox; extra == "tests"
Requires-Dist: pytest; extra == "tests"
Requires-Dist: types-PyYAML; extra == "tests"
Dynamic: license-file
